flask_aserto/__init__.py
flask_aserto/_defaults.py
flask_aserto/aio/__init__.py
flask_aserto/aio/_defaults.py
flask_aserto/aio/check.py
flask_aserto/aio/middleware.py
flask_aserto/check.py
flask_aserto/middleware.py
flask_aserto/py.typed
flask_aserto-0.32.0.dist-info/LICENSE
flask_aserto-0.32.0.dist-info/METADATA
flask_aserto-0.32.0.dist-info/WHEEL
flask_aserto-0.32.0.dist-info/RECORD
